aws_flask_swagger_ui/LICENSE
aws_flask_swagger_ui/__init__.py
aws_flask_swagger_ui/aws_api_gateway_docu.py
aws_flask_swagger_ui/flask_aws_lambda.py
aws_flask_swagger_ui/flask_swagger_ui.py
aws_flask_swagger_ui/dist/VERSION
aws_flask_swagger_ui/dist/favicon-16x16.png
aws_flask_swagger_ui/dist/favicon-32x32.png
aws_flask_swagger_ui/dist/index.css
aws_flask_swagger_ui/dist/oauth2-redirect.html
aws_flask_swagger_ui/dist/oauth2-redirect.js
aws_flask_swagger_ui/dist/swagger-initializer.js
aws_flask_swagger_ui/dist/swagger-ui-bundle.js
aws_flask_swagger_ui/dist/swagger-ui-bundle.js.map
aws_flask_swagger_ui/dist/swagger-ui-es-bundle-core.js
aws_flask_swagger_ui/dist/swagger-ui-es-bundle-core.js.map
aws_flask_swagger_ui/dist/swagger-ui-es-bundle.js
aws_flask_swagger_ui/dist/swagger-ui-es-bundle.js.map
aws_flask_swagger_ui/dist/swagger-ui-standalone-preset.js
aws_flask_swagger_ui/dist/swagger-ui-standalone-preset.js.map
aws_flask_swagger_ui/dist/swagger-ui.css
aws_flask_swagger_ui/dist/swagger-ui.css.map
aws_flask_swagger_ui/dist/swagger-ui.js
aws_flask_swagger_ui/dist/swagger-ui.js.map
aws_flask_swagger_ui/templates/index.template.html
aws_flask_swagger_ui-1.2.0.dist-info/licenses/LICENSE
aws_flask_swagger_ui-1.2.0.dist-info/METADATA
aws_flask_swagger_ui-1.2.0.dist-info/WHEEL
aws_flask_swagger_ui-1.2.0.dist-info/top_level.txt
aws_flask_swagger_ui-1.2.0.dist-info/RECORD
