Metadata-Version: 2.4
Name: aws-flask-swagger-ui
Version: 1.2.0
Summary: Swagger UI Blueprint for Flask on AWS Lambda
Home-page: https://github.com/tb102122/aws_flask_swagger_ui
Author: Tobias Bruckert
License: Apache License, Version 2.0
Keywords: flask aws amazon lambda swagger
Classifier: Framework :: Django
Classifier: Programming Language :: Python :: 3
Classifier: Development Status :: 4 - Beta
Classifier: Intended Audience :: Developers
Classifier: Programming Language :: Python :: 3
Classifier: Programming Language :: Python :: 3.11
Classifier: Programming Language :: Python :: 3.12
Classifier: Programming Language :: Python :: 3.13
Classifier: Programming Language :: Python :: 3.14
Classifier: Intended Audience :: Developers
Classifier: Natural Language :: English
Classifier: Topic :: Utilities
Classifier: License :: OSI Approved :: Apache Software License
License-File: LICENSE
Requires-Dist: Flask
Dynamic: license-file
